navdoon/__init__.py
navdoon/app.py
navdoon/collector.py
navdoon/processor.py
navdoon/server.py
navdoon/destination/__init__.py
navdoon/destination/abstract.py
navdoon/destination/file.py
navdoon/destination/graphite.py
navdoon/destination/stream.py
navdoon/pystdlib/__init__.py
navdoon/pystdlib/configparser.py
navdoon/pystdlib/queue.py
navdoon/pystdlib/typing.py
navdoon/utils/__init__.py
navdoon/utils/common.py
navdoon/utils/system.py
navdoon-0.3.0.data/scripts/navdoon
navdoon-0.3.0.dist-info/DESCRIPTION.rst
navdoon-0.3.0.dist-info/METADATA
navdoon-0.3.0.dist-info/RECORD
navdoon-0.3.0.dist-info/WHEEL
navdoon-0.3.0.dist-info/entry_points.txt
navdoon-0.3.0.dist-info/metadata.json
navdoon-0.3.0.dist-info/top_level.txt
tests/__init__.py
tests/functional_tests.py
tests/test_app.py
tests/test_collector.py
tests/test_destination.py
tests/test_processor.py
tests/test_server.py
tests/test_utils_common.py
tests/test_utils_system.py
