Metadata-Version: 2.0
Name: navdoon
Version: 0.3.0
Summary: Powerful Statsd server, made easy
Home-page: https://github.com/farzadghanei/navdoon
Author: Farzad Ghanei
Author-email: UNKNOWN
License: Apache License, Version 2.0
Keywords: statsd monitoring
Platform: UNKNOWN
Classifier: Development Status :: 4 - Beta
Classifier: Intended Audience :: Developers
Classifier: License :: OSI Approved :: Apache Software License
Classifier: Operating System :: OS Independent
Classifier: Programming Language :: Python :: 2.7
Classifier: Programming Language :: Python :: 3
Classifier: Programming Language :: Python :: 3.2
Classifier: Programming Language :: Python :: 3.3
Classifier: Programming Language :: Python :: 3.4
Classifier: Programming Language :: Python :: 3.5
Classifier: Programming Language :: Python :: 3.6
Classifier: Programming Language :: Python :: Implementation :: CPython
Classifier: Programming Language :: Python :: Implementation :: PyPy
Classifier: Topic :: Software Development :: Libraries :: Python Modules
Classifier: Topic :: System :: Networking :: Monitoring
Requires-Dist: statsdmetrics (>=0.3)
Provides-Extra: dev
Requires-Dist: coverage; extra == 'dev'
Requires-Dist: distutilazy (>=0.4.2); extra == 'dev'
Requires-Dist: typing (>=3.5.0.1); extra == 'dev'
